[
  {
    "key": "game/3 - World Map.rpy_L17_0",
    "original": "What website did you download the game from?",
    "context": "代码: https://github.com/ponytranz/FwB2CN/blob/empty/game/3%20-%20World%20Map.rpy#L17"
  },
  {
    "key": "game/3 - World Map.rpy_L17_1",
    "original": "Patreon",
    "context": "代码: https://github.com/ponytranz/FwB2CN/blob/empty/game/3%20-%20World%20Map.rpy#L17"
  },
  {
    "key": "game/3 - World Map.rpy_L17_2",
    "original": "F95zone",
    "context": "代码: https://github.com/ponytranz/FwB2CN/blob/empty/game/3%20-%20World%20Map.rpy#L17"
  },
  {
    "key": "game/3 - World Map.rpy_L17_3",
    "original": "No Thanks",
    "context": "代码: https://github.com/ponytranz/FwB2CN/blob/empty/game/3%20-%20World%20Map.rpy#L17"
  },
  {
    "key": "game/3 - World Map.rpy_L130_0",
    "original": "Gift",
    "context": "代码: https://github.com/ponytranz/FwB2CN/blob/empty/game/3%20-%20World%20Map.rpy#L130"
  },
  {
    "key": "game/3 - World Map.rpy_L130_1",
    "original": "Replay Events",
    "context": "代码: https://github.com/ponytranz/FwB2CN/blob/empty/game/3%20-%20World%20Map.rpy#L130"
  },
  {
    "key": "game/3 - World Map.rpy_L130_2",
    "original": "Sex",
    "context": "代码: https://github.com/ponytranz/FwB2CN/blob/empty/game/3%20-%20World%20Map.rpy#L130"
  },
  {
    "key": "game/3 - World Map.rpy_L130_3",
    "original": "Sleep",
    "context": "代码: https://github.com/ponytranz/FwB2CN/blob/empty/game/3%20-%20World%20Map.rpy#L130"
  },
  {
    "key": "game/3 - World Map.rpy_L130_4",
    "original": "Outside",
    "context": "代码: https://github.com/ponytranz/FwB2CN/blob/empty/game/3%20-%20World%20Map.rpy#L130"
  },
  {
    "key": "game/3 - World Map.rpy_L133_0",
    "original": "Punk Costume - Owned: [punk]",
    "context": "代码: https://github.com/ponytranz/FwB2CN/blob/empty/game/3%20-%20World%20Map.rpy#L133"
  },
  {
    "key": "game/3 - World Map.rpy_L133_1",
    "original": "Bunny Girl Costume - Owned: [bunnygirl]",
    "context": "代码: https://github.com/ponytranz/FwB2CN/blob/empty/game/3%20-%20World%20Map.rpy#L133"
  },
  {
    "key": "game/3 - World Map.rpy_L133_2",
    "original": "Pantyhose - Owned: [pantyhose]",
    "context": "代码: https://github.com/ponytranz/FwB2CN/blob/empty/game/3%20-%20World%20Map.rpy#L133"
  },
  {
    "key": "game/3 - World Map.rpy_L133_3",
    "original": "Lingerie - Owned: [lingerie]",
    "context": "代码: https://github.com/ponytranz/FwB2CN/blob/empty/game/3%20-%20World%20Map.rpy#L133"
  },
  {
    "key": "game/3 - World Map.rpy_L133_4",
    "original": "Buttplug - Owned: [buttplug]",
    "context": "代码: https://github.com/ponytranz/FwB2CN/blob/empty/game/3%20-%20World%20Map.rpy#L133"
  },
  {
    "key": "game/3 - World Map.rpy_L133_5",
    "original": "Anal Lubrication - Owned: [lubrication]",
    "context": "代码: https://github.com/ponytranz/FwB2CN/blob/empty/game/3%20-%20World%20Map.rpy#L133"
  },
  {
    "key": "game/3 - World Map.rpy_L133_6",
    "original": "Lewd Spellbook - Owned: [lewdspellbook]",
    "context": "代码: https://github.com/ponytranz/FwB2CN/blob/empty/game/3%20-%20World%20Map.rpy#L133"
  },
  {
    "key": "game/3 - World Map.rpy_L221_0",
    "original": "While replaying, you can return at any time using the phone.",
    "context": "代码: https://github.com/ponytranz/FwB2CN/blob/empty/game/3%20-%20World%20Map.rpy#L221"
  },
  {
    "key": "game/3 - World Map.rpy_L221_1",
    "original": "Replay Intro",
    "context": "代码: https://github.com/ponytranz/FwB2CN/blob/empty/game/3%20-%20World%20Map.rpy#L221"
  },
  {
    "key": "game/3 - World Map.rpy_L221_2",
    "original": "Replay [mox] & [pen] Double Blowjob",
    "context": "代码: https://github.com/ponytranz/FwB2CN/blob/empty/game/3%20-%20World%20Map.rpy#L221"
  },
  {
    "key": "game/3 - World Map.rpy_L221_3",
    "original": "Replay [mox] & [pen] Threesome",
    "context": "代码: https://github.com/ponytranz/FwB2CN/blob/empty/game/3%20-%20World%20Map.rpy#L221"
  },
  {
    "key": "game/3 - World Map.rpy_L245_0",
    "original": "Energy: [energy]",
    "context": "代码: https://github.com/ponytranz/FwB2CN/blob/empty/game/3%20-%20World%20Map.rpy#L245"
  },
  {
    "key": "game/3 - World Map.rpy_L245_1",
    "original": "No Energy Left",
    "context": "代码: https://github.com/ponytranz/FwB2CN/blob/empty/game/3%20-%20World%20Map.rpy#L245"
  },
  {
    "key": "game/3 - World Map.rpy_L245_2",
    "original": "Facesitting",
    "context": "代码: https://github.com/ponytranz/FwB2CN/blob/empty/game/3%20-%20World%20Map.rpy#L245"
  },
  {
    "key": "game/3 - World Map.rpy_L245_3",
    "original": "Legs-Up Missionary",
    "context": "代码: https://github.com/ponytranz/FwB2CN/blob/empty/game/3%20-%20World%20Map.rpy#L245"
  },
  {
    "key": "game/3 - World Map.rpy_L245_4",
    "original": "Standing From Behind",
    "context": "代码: https://github.com/ponytranz/FwB2CN/blob/empty/game/3%20-%20World%20Map.rpy#L245"
  }
]